mock_generator/__init__.py
mock_generator/analyzer.py
mock_generator/cli.py
mock_generator/exporters.py
mock_generator/generator.py
mock_generator/relationship_resolver.py
mock_generator/scanner.py
mock_generator/field_mappers/__init__.py
mock_generator/field_mappers/django_mapper.py
mock_generator/field_mappers/pydantic_mapper.py
mock_generator/field_mappers/sqlalchemy_mapper.py
ars02bahadr_mock_data_generator-0.1.0.dist-info/METADATA
ars02bahadr_mock_data_generator-0.1.0.dist-info/WHEEL
ars02bahadr_mock_data_generator-0.1.0.dist-info/entry_points.txt
ars02bahadr_mock_data_generator-0.1.0.dist-info/top_level.txt
ars02bahadr_mock_data_generator-0.1.0.dist-info/RECORD
