Metadata-Version: 2.4
Name: ars02bahadr-mock-data-generator
Version: 0.1.0
Summary: Mock data generator for Django, SQLAlchemy, and Pydantic models
Author-email: Bahadır Arslan <ostimbahadir02@gmail.com>
License: MIT
Keywords: mock,data,faker,django,sqlalchemy,pydantic,cli
Classifier: Programming Language :: Python :: 3
Classifier: Programming Language :: Python :: 3.8
Classifier: Programming Language :: Python :: 3.9
Classifier: Programming Language :: Python :: 3.10
Classifier: Programming Language :: Python :: 3.11
Classifier: License :: OSI Approved :: MIT License
Classifier: Environment :: Console
Requires-Python: >=3.8
Requires-Dist: faker>=20.0.0
Requires-Dist: click>=8.0.0
Requires-Dist: rich>=13.0.0
Requires-Dist: pydantic>=2.0.0
Provides-Extra: django
Requires-Dist: django>=3.2; extra == "django"
Provides-Extra: sqlalchemy
Requires-Dist: sqlalchemy>=2.0; extra == "sqlalchemy"
